MANIFEST.in
setup.py
create_react_redux_ecosystem.egg-info/PKG-INFO
create_react_redux_ecosystem.egg-info/SOURCES.txt
create_react_redux_ecosystem.egg-info/dependency_links.txt
create_react_redux_ecosystem.egg-info/entry_points.txt
create_react_redux_ecosystem.egg-info/top_level.txt
rrcreate_assets/create.py
rrcreate_assets/redux/.babelrc
rrcreate_assets/redux/.eslintignore
rrcreate_assets/redux/.eslintrc.js
rrcreate_assets/redux/.flowconfig
rrcreate_assets/redux/.gitignore
rrcreate_assets/redux/README.md
rrcreate_assets/redux/index.js
rrcreate_assets/redux/package.json
rrcreate_assets/redux/webpack.config.js