Metadata-Version: 1.0
Name: create-react-redux-ecosystem
Version: 0.0.1
Summary: Installing npm modules of react and redux
Home-page: UNKNOWN
Author: UNKNOWN
Author-email: UNKNOWN
License: MIT
Platform: UNKNOWN
